zinley/__init__.py
zinley/__main__.py
zinley/cli.py
zinley/version.py
zinley_cli-0.1.20.dist-info/LICENSE
zinley_cli-0.1.20.dist-info/METADATA
zinley_cli-0.1.20.dist-info/WHEEL
zinley_cli-0.1.20.dist-info/entry_points.txt
zinley_cli-0.1.20.dist-info/top_level.txt
zinley_cli-0.1.20.dist-info/RECORD
