Metadata-Version: 2.1
Name: zinley-cli
Version: 0.1.20
Classifier: Programming Language :: Python :: 3
Classifier: License :: OSI Approved :: MIT License
Classifier: Operating System :: OS Independent
Requires-Python: >=3.6
License-File: LICENSE
Requires-Dist: typer==0.12.5
Requires-Dist: fsd==0.1.526
